[{"image":"https://i.ibb.co/5RdGH3C/31a29a3347d3.jpg","description":"Egate i9 Pro-Max HD 720p (3300 lm / 1 Speaker / Remote ...","color":"White","stars":4.1,"reviews":"(1,284)","new_price":899,"old_price":1299,"discount":30,"delivery_type":"Free delivery","hidden_stars":4.1,"item_id":1},{"image":"https://i.ibb.co/TkRggQ4/d5415a9e96be.jpg","description":"Like Star INI-Pro YG300 (600 lm) Portable Projector","color":"Multicolor","stars":3.5,"reviews":"(449)","new_price":349,"old_price":4999,"discount":39,"delivery_type":"Free delivery","hidden_stars":3.5,"item_id":2},{"image":"https://i.ibb.co/hCzMyvX/01bf8c55522d.jpg","description":"Technuv YG300 400LM Portable Mini Home Theater LED Proj...","color":"Multicolor","stars":3.6,"reviews":"(75)","new_price":349,"old_price":9999,"discount":69,"delivery_type":"Free delivery","hidden_stars":3.6,"item_id":3},{"image":"https://i.ibb.co/zSGtmg7/a4d6c7932c92.jpg","description":"PLAY MP6 Brand New FHD LED 3D 300' Display WiFi Project...","color":"White/Black","stars":3.5,"reviews":"(59)","new_price":1545,"old_price":75,"discount":85,"delivery_type":"Free delivery","hidden_stars":3.5,"item_id":4},{"image":"https://i.ibb.co/ysLfqJW/47605a8d3037.jpg","description":"Rigal RD-810 LED with HDMI,VGA,AV, USB White (1000 lm /...","color":"White","stars":3.9,"reviews":"(488)","new_price":4655,"old_price":945,"discount":50,"delivery_type":"Free delivery","hidden_stars":3.9,"item_id":5},{"image":"https://i.ibb.co/jLP28q4/a7201d75d59d.jpg","description":"Torexo Sales T10 FullHD 1920*1080P Android Projector, 2...","color":"White, Black","stars":4.5,"reviews":"(76)","new_price":13499,"old_price":21999,"discount":38,"delivery_type":"Free delivery","hidden_stars":4.5,"item_id":6},{"image":"https://i.ibb.co/THM9Mx8/ee8aaba56f4d.jpg","description":"IBS BEST QUALITY T 300 LED Projector Mini Portable Proj...","color":"Yellow","stars":3.4,"reviews":"(277)","new_price":3499,"old_price":5999,"discount":41,"delivery_type":"Free delivery","hidden_stars":3.4,"item_id":7},{"image":"https://i.ibb.co/VMnxfh6/448c7b140dc0.jpg","description":"PLAY MP1-A Smart WIFI 3D 4k Full HD LED Recently Launch...","color":"White","stars":4.1,"reviews":"(109)","new_price":1799,"old_price":5,"discount":65,"delivery_type":"Free delivery","hidden_stars":4.1,"item_id":8},{"image":"https://i.ibb.co/bL8fVxb/a202739056f8.jpg","description":"ZEBRONICS Zeb-Pixa Play 12 with Dolby Audio Support & 7...","color":"Black","stars":4.1,"reviews":"(548)","new_price":11499,"old_price":21999,"discount":47,"delivery_type":"Free delivery","hidden_stars":4.1,"item_id":9},{"image":"https://i.ibb.co/bzPSgQ7/64de06494e0f.jpg","description":"ZEBRONICS ZEB-LP2000M (2000 lm / Wireless / Remote Cont...","color":"Black :: Silver","stars":3.6,"reviews":"(180)","new_price":8499,"old_price":16999,"discount":50,"delivery_type":"Free delivery","hidden_stars":3.6,"item_id":10},{"image":"https://i.ibb.co/Wv86h8r/725e98f6cfbd.jpg","description":"IBS BEST QUALITY T 300 LED Projector Mini Portable Proj...","color":"Black","stars":3.4,"reviews":"(277)","new_price":3499,"old_price":5999,"discount":41,"delivery_type":"Free delivery","hidden_stars":3.4,"item_id":11},{"image":"https://i.ibb.co/kxTBSCj/6890c85b32a5.jpg","description":"ZuZu Smart Wifi Easy pairing with your mobile phone bui...","color":"Black","new_price":995,"old_price":295,"discount":66,"delivery_type":"Free delivery","hidden_stars":4.3,"item_id":12},{"image":"https://i.ibb.co/bHJ0b2w/28fc733f4e6c.jpg","description":"ZEBRONICS ZEB-LP2800HD (2800 lm) 720p HD||Built-in-Spea...","color":"Black","stars":4,"reviews":"(439)","new_price":1999,"old_price":15999,"discount":31,"delivery_type":"Free delivery","hidden_stars":4,"item_id":13},{"image":"https://i.ibb.co/FDGy6k7/2ed45b7f7bca.jpg","description":"the easy shop Aluminium Alloy Usb Adjustable Romantic S...","color":"Black","stars":4,"reviews":"(12)","new_price":175,"old_price":499,"discount":64,"delivery_type":"Free delivery","hidden_stars":4,"item_id":14},{"image":"https://i.ibb.co/q0x7QkN/5f7b0cc3e70b.jpg","description":"WRADER Flexible 360 Degree Adjustable USB Star Light Ca...","color":"Black","stars":3,"reviews":"(25)","new_price":249,"old_price":499,"discount":50,"hidden_stars":3,"item_id":15},{"image":"https://i.ibb.co/7RJ94TC/954f91bccff6.jpg","description":"BOSS S12 Full HD 3D 2500 Lumens (3000 lm / Remote Contr...","color":"White","stars":4.2,"reviews":"(85)","new_price":1374,"old_price":75,"discount":81,"delivery_type":"Free delivery","hidden_stars":4.2,"item_id":16},{"image":"https://i.ibb.co/Ph6j2Cw/15cb4cbc3211.jpg","description":"MOIZ 84 Inch Projector Screen (Foldable) 6 x 4 Feet 4:3...","stars":4.2,"reviews":"(5)","new_price":754,"old_price":3499,"discount":78,"delivery_type":"Free delivery","hidden_stars":4.2,"item_id":17},{"image":"https://i.ibb.co/x2MFJ8w/9a6c799ee0c9.jpg","description":"LipiWorld MW516 MS513 MX514 DLP Projector Remote Contro...","color":"Black","stars":4.5,"reviews":"(44)","new_price":699,"old_price":1499,"discount":53,"delivery_type":"Free delivery","hidden_stars":4.5,"item_id":18},{"image":"https://i.ibb.co/KhhChf9/ac8477b85d59.jpg","description":"VRUM mini projector t300 model (3000 lm) Portable Proje...","color":"Black","stars":4.3,"reviews":"(3)","new_price":298,"old_price":4999,"discount":40,"delivery_type":"Free delivery","hidden_stars":4.3,"item_id":19},{"image":"https://i.ibb.co/CKcqSzc/64aecba53aa7.jpg","description":"BOSS S41A | 3840x2160p| Android: 6.0 | 5000 Lumens | 50...","color":"White","new_price":22499,"old_price":175,"discount":87,"delivery_type":"Free delivery","hidden_stars":4.2,"item_id":20},{"image":"https://i.ibb.co/yQCf2qF/a65c4a781c5d.jpg","description":"IBS UC 500 PROJECTOR, 400LM Portable Mini Home Theater ...","color":"yellow white","stars":3.4,"reviews":"(85)","new_price":3299,"old_price":9999,"discount":67,"delivery_type":"Free delivery","hidden_stars":3.4,"item_id":21},{"image":"https://i.ibb.co/1RX7h0k/a0d943341e38.jpg","description":"Livato Y6 Full HD 1080p Modulated at 720p 8000 Lumens H...","color":"White, Black","stars":3.9,"reviews":"(233)","new_price":8999,"old_price":14999,"discount":40,"delivery_type":"Free delivery","hidden_stars":3.9,"item_id":22},{"image":"https://i.ibb.co/wNXSmHv/8d762696b340.jpg","description":"Torexo Sales TS82 BASIC 720p HD (1080p Support) with 20...","color":"TS82 BASIC","stars":4.2,"reviews":"(5)","new_price":7399,"old_price":14999,"discount":50,"delivery_type":"Free delivery","hidden_stars":4.2,"item_id":23},{"image":"https://i.ibb.co/0sdQMWb/6ba9daac69fa.jpg","description":"XElectron S2 Miracast/Airplay HD 720p (2600 lm / 2 Spea...","color":"Blue","stars":4,"reviews":"(5)","new_price":799,"old_price":11999,"discount":33,"delivery_type":"Free delivery","hidden_stars":4,"item_id":24},{"image":"https://i.ibb.co/hmXfp6D/210f87ce5bb6.jpg","description":"IBS BEST QUALITY T6 WIFI LED Projector 1080p Full HD wi...","color":"White","stars":3.4,"reviews":"(51)","new_price":6998,"old_price":9999,"discount":30,"delivery_type":"Free delivery","hidden_stars":3.4,"item_id":25},{"image":"https://i.ibb.co/2ZDVQj4/3db96ff434c8.jpg","description":"ZEBRONICS ZEB-LP2000M (2000 lm / Wireless / Remote Cont...","color":"Black, Blue","stars":3.6,"reviews":"(180)","new_price":8499,"old_price":16999,"discount":50,"delivery_type":"Free delivery","hidden_stars":3.6,"item_id":26},{"image":"https://i.ibb.co/KVy5XT2/e92928e2bcc3.jpg","description":"VISITEK V12 Android Full HD 1080p Native 4k Support (70...","color":"Black","stars":4.8,"reviews":"(4)","new_price":29,"old_price":3999,"discount":47,"delivery_type":"Free delivery","hidden_stars":4.8,"item_id":27},{"image":"https://i.ibb.co/dkYsBT2/4253a8ce169a.jpg","description":"PLAY MP1 Full HD LED Recently Launched Projector 4D key...","color":"White and Black, White, Black, Silver","stars":3.9,"reviews":"(58)","new_price":16999,"old_price":5,"discount":66,"delivery_type":"Free delivery","hidden_stars":3.9,"item_id":28},{"image":"https://i.ibb.co/LPf6P77/28da40daf681.jpg","description":"IBS T 300 LED Projector Mini Portable Projection Device...","color":"Yellow","stars":3.1,"reviews":"(89)","new_price":3699,"old_price":5999,"discount":38,"delivery_type":"Free delivery","hidden_stars":3.1,"item_id":29},{"image":"https://i.ibb.co/qJ7JyBT/641f47a8928f.jpg","description":"IBS T 300 LED Projector Mini Portable Projection Device...","color":"Black","stars":3.1,"reviews":"(89)","new_price":3699,"old_price":9999,"discount":63,"delivery_type":"Free delivery","hidden_stars":3.1,"item_id":30},{"image":"https://i.ibb.co/wLPyQ48/dade8201d21d.jpg","description":"XElectron C9 Miracast Airplay LED Projector (3800 lm / ...","color":"White","stars":3.8,"reviews":"(126)","new_price":189,"old_price":14999,"discount":27,"delivery_type":"Free delivery","hidden_stars":3.8,"item_id":31},{"image":"https://i.ibb.co/P4zMNgx/c67361f0c8d1.jpg","description":"BOSS S3_00003_A_Black (2000 lm) Portable Projector","color":"Black","new_price":18899,"old_price":25,"discount":24,"delivery_type":"Free delivery","hidden_stars":4.2,"item_id":32},{"image":"https://i.ibb.co/6yyRwPy/fae9843fa610.jpg","description":"WRADER UPGRADED VERSION 2.O USB LED Star Light Projecto...","color":"Black","stars":3,"reviews":"(50)","new_price":238,"old_price":599,"discount":60,"hidden_stars":3,"item_id":33},{"image":"https://i.ibb.co/yQH5XGZ/298f91570991.jpg","description":"MOIZ 150\" Inch Projector Screen (Foldable) 10 x 8 Feet ...","stars":4.2,"reviews":"(32)","new_price":3464,"old_price":9999,"discount":65,"delivery_type":"Free delivery","hidden_stars":4.2,"item_id":34},{"image":"https://i.ibb.co/smkxT6Y/c65b8bee6837.jpg","description":"MOIZ 100\" Inch Projector Screen (Foldable) 7 x 5 Feet 4...","stars":4.2,"reviews":"(37)","new_price":1199,"old_price":4999,"discount":76,"delivery_type":"Free delivery","hidden_stars":4.2,"item_id":35},{"image":"https://i.ibb.co/WgBpJj7/77b5deb1c17e.jpg","description":"PLAY MP1 Newest WiFi Native Full HD Led Advance Project...","color":"White/ Black","stars":4,"reviews":"(248)","new_price":168,"old_price":75,"discount":77,"delivery_type":"Free delivery","hidden_stars":4,"item_id":36},{"image":"https://i.ibb.co/JtYQ5q2/12cf03c458c4.jpg","description":"Sii Space Saving Portable/5 feet Height Adjustable Lapt...","stars":3.6,"reviews":"(9)","new_price":31,"old_price":35,"discount":11,"delivery_type":"Free delivery","hidden_stars":3.6,"item_id":37},{"image":"https://i.ibb.co/frRYvjY/1ef88e9dbb4d.jpg","description":"Livato T4 Full HD Wifi Inbuilt Youtube (3998 lm / 1 Spe...","color":"Blue","stars":3.9,"reviews":"(33)","new_price":6498,"old_price":14999,"discount":56,"delivery_type":"Free delivery","hidden_stars":3.9,"item_id":38},{"image":"https://i.ibb.co/W2hgVgg/44eea2a0ef1b.jpg","description":"Egate K9 Android HD 720p (4000 lm / 2 Speaker / Wireles...","color":"Black","stars":3.9,"reviews":"(368)","new_price":1399,"old_price":1999,"discount":30,"delivery_type":"Free delivery","hidden_stars":3.9,"item_id":39},{"image":"https://i.ibb.co/6rFLxc5/49992e986108.jpg","description":"BOSS S31A | 3840x2160P Ultra HD | Contrast Ratio: 7000:...","color":"White","new_price":31229,"old_price":11,"discount":71,"delivery_type":"Free delivery","hidden_stars":3.7,"item_id":40},{"image":"https://i.ibb.co/zhpHQQJ/ec136b60fd54.jpg","description":"XElectron S1 HD 720p (2600 lm / 2 Speaker / Remote Cont...","color":"White, Black","stars":3.7,"reviews":"(6)","new_price":699,"old_price":1999,"discount":36,"delivery_type":"Free delivery","hidden_stars":3.7,"item_id":41},{"image":"https://i.ibb.co/7CM4XL2/05d5fdaebc09.jpg","description":"IBS WIFI Mini Projector ,1080P HD Portable Projector wi...","color":"Black","stars":3.5,"reviews":"(116)","new_price":7999,"old_price":14999,"discount":46,"delivery_type":"Free delivery","hidden_stars":3.5,"item_id":42},{"image":"https://i.ibb.co/R3S854S/fa4ac4414647.jpg","description":"Egate i9 pro hd 720p-2yrs wrt (2400 L / 1 Speaker / Rem...","color":"Black","stars":4,"reviews":"(6,051)","new_price":799,"old_price":999,"discount":20,"delivery_type":"Free delivery","hidden_stars":4,"item_id":43},{"image":"https://i.ibb.co/y47bZ4N/36fbd725e687.jpg","description":"PLAY 2022 PP9 Full HD 1080p Projector for Home Office C...","color":"Black/Silver","stars":3.4,"reviews":"(48)","new_price":1121,"old_price":15,"discount":92,"delivery_type":"Free delivery","hidden_stars":3.4,"item_id":44},{"image":"https://i.ibb.co/SKHbxm5/7349dac82a8d.jpg","description":"IBS T5 Smart Projector HD 3D WiFi miracast 3200 Lumens ...","color":"White","stars":3.5,"reviews":"(303)","new_price":6998,"old_price":12999,"discount":46,"delivery_type":"Free delivery","hidden_stars":3.5,"item_id":45},{"image":"https://i.ibb.co/4FkCFmf/0d147c531195.jpg","description":"VISITEK V6 Smart Android HD 720p (1080p Support) | 3300...","color":"Black","stars":3.9,"reviews":"(327)","new_price":1299,"old_price":2,"discount":35,"delivery_type":"Free delivery","hidden_stars":3.9,"item_id":46},{"image":"https://i.ibb.co/6WrMsGY/08673de6a34c.jpg","description":"IBS T500 Mini Projector LED Portable Projector Home USB...","color":"Yellow","stars":3,"reviews":"(70)","new_price":3999,"old_price":9999,"discount":60,"delivery_type":"Free delivery","hidden_stars":3,"item_id":47},{"image":"https://i.ibb.co/2kDYkTf/bb95064cbe0b.jpg","description":"BOSS S8_0008 (2000 lm / 1 Speaker) Portable Projector","color":"Black","stars":3.1,"reviews":"(7)","new_price":22796,"old_price":49,"discount":53,"delivery_type":"Free delivery","hidden_stars":3.1,"item_id":48},{"image":"https://i.ibb.co/ydf0v4q/1a1b6fbbc241.jpg","description":"IBS T5 Smart Projector HD 3D WiFi miracast 3200 Lumens ...","color":"White","stars":3.6,"reviews":"(145)","new_price":6998,"old_price":12999,"discount":46,"delivery_type":"Free delivery","hidden_stars":3.6,"item_id":49},{"image":"https://i.ibb.co/6W03ZPK/556d84711f08.jpg","description":"Clubics Portable Mini Latest LED Projector with 1080p V...","color":"Yellow","new_price":2789,"old_price":3999,"discount":30,"delivery_type":"Free delivery","hidden_stars":3.6,"item_id":50},{"image":"https://i.ibb.co/BNfHpMG/39cabe62248d.jpg","description":"IBS UC 500 PROJECTOR, 400LM Portable Mini Home Theater ...","color":"Yellow","stars":3.1,"reviews":"(114)","new_price":3199,"old_price":6999,"discount":54,"hidden_stars":3.1,"item_id":51},{"image":"https://i.ibb.co/3NC6rzw/be41858944c4.jpg","description":"PLAY Portable 4 Inch Mini 1080P High Definition WIFI Pr...","color":"White","stars":4.6,"reviews":"(7)","new_price":148,"old_price":5,"discount":70,"delivery_type":"Free delivery","hidden_stars":4.6,"item_id":52},{"image":"https://i.ibb.co/HD3HCtd/053e8cde2d67.jpg","description":"MOIZ 84 Inch Projector Screen (Foldable) 6 x 4 Feet 4:3...","stars":3.7,"reviews":"(25)","new_price":84,"old_price":3199,"discount":74,"delivery_type":"Free delivery","hidden_stars":3.7,"item_id":53},{"image":"https://i.ibb.co/Bckyxsk/ca182eebacb7.jpg","description":"ANDTRONICS Premium VGA To VGA 15 Pin CABLE Compatible f...","color":"Compatible with Desktops, Laptops, Servers, Gaming Consoles, TV, Black, One Cable","new_price":1457,"old_price":4,"discount":63,"delivery_type":"Free delivery","hidden_stars":4.4,"item_id":54},{"image":"https://i.ibb.co/Y3mV1F1/2621aa562f4d.jpg","description":"RGL 3E Android 5000 mAh Portable Wifi Bluetooth Cordles...","color":"White, Black","stars":3.1,"reviews":"(7)","new_price":1999,"old_price":2999,"discount":33,"delivery_type":"Free delivery","hidden_stars":3.1,"item_id":55},{"image":"https://i.ibb.co/Xs6M3Kq/57c23efc802f.jpg","description":"BOSS S27A| 60,000 Life Hrs, 7000 Lumens, 9000:1 Contras...","color":"Grey","new_price":31994,"old_price":145,"discount":77,"delivery_type":"Free delivery","hidden_stars":3.8,"item_id":56},{"image":"https://i.ibb.co/kKgvZFy/230ee30c0966.jpg","description":"BOSS S13A Latest FHD 3D Android Smart Wi-Fi Bluetooth P...","color":"White","stars":4.1,"reviews":"(77)","new_price":24999,"old_price":125,"discount":80,"delivery_type":"Free delivery","hidden_stars":4.1,"item_id":57},{"image":"https://i.ibb.co/CKNwXhK/31557c3060c5.jpg","description":"LG PH510PG-GL.ATRLLAN (550 lm / 2 Speaker / Wireless / ...","color":"White","stars":4.6,"reviews":"(22)","new_price":43599,"old_price":55,"discount":20,"delivery_type":"Free delivery","hidden_stars":4.6,"item_id":58},{"image":"https://i.ibb.co/zSGtmg7/a4d6c7932c92.jpg","description":"PLAY MP6 Brand New FHD LED 3D 300' Display WiFi Project...","color":"White/Black","stars":3.5,"reviews":"(59)","new_price":1545,"old_price":75,"discount":85,"delivery_type":"Free delivery","hidden_stars":3.5,"item_id":59},{"image":"https://i.ibb.co/7RJ94TC/954f91bccff6.jpg","description":"BOSS S12 Latest Year 2021 FHD 3D Projector | 3100 Lumen...","color":"White","stars":3.5,"reviews":"(10)","new_price":14399,"old_price":79999,"discount":82,"delivery_type":"Free delivery","hidden_stars":3.5,"item_id":60},{"image":"https://i.ibb.co/rskjwvr/32895d26cdce.jpg","description":"Zync T5 WiFi Portable Home Cinema Projector (2800 lm / ...","color":"White, Black","stars":3.8,"reviews":"(48)","new_price":6349,"old_price":11999,"discount":47,"delivery_type":"Free delivery","hidden_stars":3.8,"item_id":61},{"image":"https://i.ibb.co/hM4fXPD/05a0ebce309e.jpg","description":"Nebula Apollo (200 lm / 1 Speaker / Wireless / Remote C...","color":"Black","stars":4.3,"reviews":"(41)","new_price":34999,"old_price":39999,"discount":12,"delivery_type":"Free delivery","hidden_stars":4.3,"item_id":62},{"image":"https://i.ibb.co/QYp6N1z/8509170262b8.jpg","description":"Torexo Sales TS82 Basic HD 720p (1080p Support) | 4000L...","color":"White","stars":4.4,"reviews":"(74)","new_price":7399,"old_price":14999,"discount":50,"delivery_type":"Free delivery","hidden_stars":4.4,"item_id":63},{"image":"https://i.ibb.co/hsbpDGF/de76548593e9.jpg","description":"PLAY PP10A New Android 6.0 Advance Technology High Defi...","color":"White","stars":3.4,"reviews":"(19)","new_price":19999,"old_price":5,"discount":60,"delivery_type":"Free delivery","hidden_stars":3.4,"item_id":64},{"image":"https://i.ibb.co/wNyCzSx/e367d56945f4.jpg","description":"BOSS S22A | Android 6 | 3D Full HD 1980 x 1080p | Contr...","color":"Black","stars":2.3,"reviews":"(3)","new_price":13499,"old_price":5,"discount":73,"delivery_type":"Free delivery","hidden_stars":2.3,"item_id":65},{"image":"https://i.ibb.co/9q7dBN7/a5bfcec2011e.jpg","description":"EG 6X Miracast (3200 lm / 1 Speaker / Wireless / Remote...","color":"Black","stars":3.9,"reviews":"(78)","new_price":799,"old_price":999,"discount":20,"delivery_type":"Free delivery","hidden_stars":3.9,"item_id":66},{"image":"https://i.ibb.co/ZH9Ktcp/2b82c5ae893f.jpg","description":"MAINDAIS MND-E03i31 Projector Screen (Width 22 cm x 9.4...","new_price":259,"old_price":999,"discount":74,"delivery_type":"Free delivery","hidden_stars":3.8,"item_id":67},{"image":"https://i.ibb.co/YL0dqK6/37e3f10467a9.jpg","description":"PLAY MP4 Latest Android 9.0 Advance Technology 4k 3D Fu...","color":"Black","stars":4,"reviews":"(34)","new_price":2945,"old_price":75,"discount":60,"delivery_type":"Free delivery","hidden_stars":4,"item_id":68},{"image":"https://i.ibb.co/9rjCq0M/45903b2da262.jpg","description":"MOIZ 84\" Inch Projector Screen (Foldable) 6 x 4 Feet 4:...","stars":3.9,"reviews":"(511)","new_price":78,"old_price":2999,"discount":73,"delivery_type":"Free delivery","hidden_stars":3.9,"item_id":69},{"image":"https://i.ibb.co/RTJmWhc/d250d28403a8.jpg","description":"RANWAR Eyelet Foldable Projector Screen 4:3 Aspect Rati...","stars":3.8,"reviews":"(164)","new_price":9,"old_price":2999,"discount":69,"delivery_type":"Free delivery","hidden_stars":3.8,"item_id":70},{"image":"https://i.ibb.co/q7C4Tr9/404a9f5bb665.jpg","description":"LipiWorld RM-PJ6 Remote Control Compatible for  Project...","color":"Gray","stars":3.9,"reviews":"(7)","new_price":599,"old_price":999,"discount":40,"delivery_type":"Free delivery","hidden_stars":3.9,"item_id":71},{"image":"https://i.ibb.co/1RX7h0k/a0d943341e38.jpg","description":"Livato Y6 Full HD 1080p Modulated at 720p 8000 Lumens H...","color":"White, Black","stars":3.9,"reviews":"(233)","new_price":8999,"old_price":14999,"discount":40,"delivery_type":"Free delivery","hidden_stars":3.9,"item_id":72},{"image":"https://i.ibb.co/VMnxfh6/448c7b140dc0.jpg","description":"PLAY MP1-A Smart WIFI 3D 4k Full HD LED Recently Launch...","color":"White","stars":4.1,"reviews":"(109)","new_price":1799,"old_price":5,"discount":65,"delivery_type":"Free delivery","hidden_stars":4.1,"item_id":73},{"image":"https://i.ibb.co/nr4b6y0/15203c7eceea.jpg","description":"TSPL Mini Projector (3000 lm) Portable Projector","color":"Yellow","new_price":325,"old_price":4999,"discount":39,"delivery_type":"Free delivery","hidden_stars":3.8,"item_id":74},{"image":"https://i.ibb.co/gJtsv5m/aa1fa2f1a3e4.jpg","description":"Livato T300 Mini (800 lm / Remote Controller) Portable ...","color":"Black","stars":3.5,"reviews":"(118)","new_price":399,"old_price":9999,"discount":69,"delivery_type":"Free delivery","hidden_stars":3.5,"item_id":75},{"image":"https://i.ibb.co/wLPyQ48/dade8201d21d.jpg","description":"XElectron C9 Miracast Airplay LED Projector (3800 lm / ...","color":"White","stars":3.8,"reviews":"(126)","new_price":189,"old_price":14999,"discount":27,"delivery_type":"Free delivery","hidden_stars":3.8,"item_id":76},{"image":"https://i.ibb.co/VWSvnhk/34704afa6f10.jpg","description":"Shopexo T6 Android Full HD (4000 lm / 2 Speaker / Wirel...","color":"Silver","stars":3.6,"reviews":"(25)","new_price":9999,"old_price":18999,"discount":47,"delivery_type":"Free delivery","hidden_stars":3.6,"item_id":77},{"image":"https://i.ibb.co/jMzFy40/f38342bceb33.jpg","description":"BORSSO BS30 Android 9, 1080p Native Full HD, 7200 Lumen...","color":"Black","stars":4.5,"reviews":"(8)","new_price":24999,"old_price":45999,"discount":45,"delivery_type":"Free delivery","hidden_stars":4.5,"item_id":78},{"image":"https://i.ibb.co/mysQ3Rt/074650e2d178.jpg","description":"IBS T 300 LED Projector Mini Portable Projection Device...","color":"Yellow","stars":3.2,"reviews":"(141)","new_price":3299,"old_price":9999,"discount":67,"delivery_type":"Free delivery","hidden_stars":3.2,"item_id":79},{"image":"https://i.ibb.co/0sdQMWb/6ba9daac69fa.jpg","description":"XElectron S2 Miracast/Airplay HD 720p (2600 lm / 2 Spea...","color":"Blue","stars":4,"reviews":"(5)","new_price":799,"old_price":11999,"discount":33,"delivery_type":"Free delivery","hidden_stars":4,"item_id":80}]