[{"image":"https://i.ibb.co/7S1vPPM/07573a7a4191.jpg","brand":"Goldstar","description":"Medium 29 L Laptop Backpack Goldstarbags MEDIUM 30L lap...","new_price":798,"old_price":1999,"discount":60,"delivery_type":"Free delivery","hidden_stars":3.9,"item_id":1},{"image":"https://i.ibb.co/hDVSC9N/b810dca87b90.jpg","brand":"Isparro","description":"Large 35 L Laptop Backpack Stylish Light Weight Backpac...","new_price":524,"old_price":17,"discount":69,"delivery_type":"Free delivery","hidden_stars":4.1,"item_id":2},{"image":"https://i.ibb.co/cwZSFbS/ab3659e61750.jpg","brand":"Flycraft","description":"Medium 30 L Laptop Backpack simna.1550/1 navy blue yell...","new_price":529,"old_price":1599,"discount":66,"delivery_type":"Free delivery","hidden_stars":3.6,"item_id":3},{"image":"https://i.ibb.co/MfwW8qc/2cf8fb3fd474.jpg","brand":"AMERICAN TOURISTER","description":"32.5 L Backpack Fizz Sch Bag","new_price":189,"old_price":23,"discount":52,"delivery_type":"Free delivery","hidden_stars":4.4,"item_id":4},{"image":"https://i.ibb.co/FwhPZx0/2a303a406383.jpg","brand":"NorthZone","description":"Large 35 L Backpack Waterproof Laptop Bag/Backpack for ...","new_price":635,"old_price":1999,"discount":68,"delivery_type":"Free delivery","hidden_stars":4.3,"item_id":5},{"image":"https://i.ibb.co/x3yLJ5p/e67755d45ba6.jpg","brand":"SAFARI","description":"Large 38 L Backpack 19 CASUAL BACKPACK BLUE","new_price":839,"old_price":2348,"discount":64,"delivery_type":"Free delivery","hidden_stars":3.6,"item_id":6},{"image":"https://i.ibb.co/Hr2V3Jn/bd60a9587068.jpg","brand":"SAFARI","description":"Small 15 L Backpack DAYPACK","new_price":365,"old_price":799,"discount":54,"delivery_type":"Free delivery","hidden_stars":3.6,"item_id":7},{"image":"https://i.ibb.co/mBPxxkG/f9a0a3788299.jpg","description":"30 L Casual Waterproof Laptop Backpack/Office Bag/Schoo...","new_price":37,"old_price":1999,"discount":81,"delivery_type":"Free delivery","hidden_stars":4,"item_id":8},{"image":"https://i.ibb.co/YPGbbBZ/87053ad11608.jpg","brand":"Flycraft","description":"Medium 30 L Laptop Backpack simna.1361/2 red grey casua...","new_price":527,"old_price":1199,"discount":56,"delivery_type":"Free delivery","hidden_stars":4.3,"item_id":9},{"image":"https://i.ibb.co/XkXpd3Z/1af585e09206.jpg","brand":"Blowzy","description":"Brown Men & Women Sling Bag - Extra Spacious","new_price":426,"old_price":1999,"discount":78,"delivery_type":"Free delivery","hidden_stars":4.2,"item_id":10},{"image":"https://i.ibb.co/xH7f1J6/b0c9898f6fed.jpg","brand":"GOLD SKY","description":"Brown Men Sling Bag - Extra Spacious","new_price":474,"old_price":2299,"discount":79,"delivery_type":"Free delivery","hidden_stars":4.4,"item_id":11},{"image":"https://i.ibb.co/CmYJzt0/f6f9a662ba32.jpg","brand":"Goldstar","description":"Medium 30 L Laptop Backpack 30 L Casual Waterproof Lapt...","new_price":495,"old_price":1999,"discount":75,"delivery_type":"Free delivery","hidden_stars":4.4,"item_id":12},{"image":"https://i.ibb.co/MMwkvK7/611f7021bde6.jpg","brand":"Straplt","description":"Black Men & Women Sling Bag - Regular Size","new_price":199,"old_price":799,"discount":75,"hidden_stars":3.9,"item_id":13},{"image":"https://i.ibb.co/sJsrD1Q/6052595b86f6.jpg","brand":"Atipriya","description":"Multicolor Men & Women Sling Bag","new_price":299,"old_price":85,"discount":64,"delivery_type":"Free delivery","hidden_stars":3.9,"item_id":14},{"image":"https://i.ibb.co/K2hsqD6/9bfdb6118a01.jpg","brand":"Venture Crafts","description":"Brown Men Sling Bag - Extra Spacious","new_price":388,"old_price":1899,"discount":79,"delivery_type":"Free delivery","hidden_stars":3.9,"item_id":15},{"image":"https://i.ibb.co/RPLyJyF/da442f433c04.jpg","brand":"Goldstar","description":"Medium 30 L Laptop Backpack Medium 30 L Laptop Backpack...","new_price":499,"old_price":1999,"discount":75,"delivery_type":"Free delivery","hidden_stars":4,"item_id":16},{"image":"https://i.ibb.co/LnFgs9Z/921798e06f45.jpg","brand":"facto","description":"22 L Gym Duffel Bag - boys and girl collage bag school ...","new_price":39,"old_price":1999,"discount":80,"delivery_type":"Free delivery","hidden_stars":3.9,"item_id":17},{"image":"https://i.ibb.co/XpmvVP9/623966ee46d2.jpg","brand":"Sfane","description":"25 L Gym Duffel Bag - Sports Duffel - Grey, Black","new_price":389,"old_price":1149,"discount":66,"delivery_type":"Free delivery","hidden_stars":3.7,"item_id":18},{"image":"https://i.ibb.co/1dHtXPr/564b722575b2.jpg","brand":"SAMTROH","description":"Men Casual Brown Artificial Leather Money Clip - Mini","new_price":219,"old_price":999,"discount":78,"delivery_type":"Free delivery","hidden_stars":4.2,"item_id":19},{"image":"https://i.ibb.co/1LVqQ2N/0db3e279446e.jpg","brand":"AFN FASHION","description":"Large 50 L Laptop Backpack Travel Laptop Backpack for O...","new_price":664,"old_price":1999,"discount":66,"delivery_type":"Free delivery","hidden_stars":4,"item_id":20},{"image":"https://i.ibb.co/ZX6qv72/35af49c79ad3.jpg","brand":"Mi","description":"Small 12 L Backpack Step Out 12 liters Water Repellent ...","new_price":349,"old_price":499,"discount":30,"delivery_type":"Buy 2 items, save extra 5%","hidden_stars":4.2,"item_id":21},{"image":"https://i.ibb.co/8dswTn7/315412ba7ad0.jpg","brand":"Arctic Fox","description":"Small 15 L Backpack Black Drawstring Bag","new_price":217,"old_price":349,"discount":37,"delivery_type":"Free delivery","hidden_stars":4.2,"item_id":22},{"image":"https://i.ibb.co/M6F6tGY/2b1fa147728c.jpg","brand":"DRAZO","description":"Medium 25 L Backpack DRZ_1004_NAVY","new_price":359,"old_price":1299,"discount":72,"hidden_stars":4.1,"item_id":23},{"image":"https://i.ibb.co/jrs8yvM/94d6cac897c6.jpg","brand":"Red Lemon","description":"Large 45 L Laptop Backpack RL KaKa Travel Trekking","new_price":1996,"old_price":599,"discount":66,"delivery_type":"Free delivery","hidden_stars":3.8,"item_id":24},{"image":"https://i.ibb.co/SX1025G/03051a84b0f9.jpg","brand":"Lunar","description":"Large 35 L Backpack Comet","new_price":756,"old_price":1699,"discount":55,"delivery_type":"Free delivery","hidden_stars":4,"item_id":25},{"image":"https://i.ibb.co/TLF3XQy/09010dc57ee1.jpg","brand":"Flycraft","description":"Large 35 L Laptop Backpack simn.1552/1 orange black off...","new_price":699,"old_price":2699,"discount":74,"delivery_type":"Free delivery","hidden_stars":3.9,"item_id":26},{"image":"https://i.ibb.co/BwnrjBn/569ae55d02ff.jpg","brand":"SAFARI","description":"Medium 29 L Backpack SPREEUSB 19 CASUAL BACKPACK BLUE","new_price":859,"old_price":2599,"discount":66,"delivery_type":"Free delivery","hidden_stars":4,"item_id":27},{"image":"https://i.ibb.co/X8C3HvX/0ed4ad97ab58.jpg","brand":"Goldstar","description":"Medium 30 L Laptop Backpack 30 L Casual Waterproof Lapt...","new_price":49,"old_price":1999,"discount":75,"delivery_type":"Free delivery","hidden_stars":3.9,"item_id":28},{"image":"https://i.ibb.co/5T3XNnJ/24f80be4aea7.jpg","brand":"made by heart","description":"Blue Men Sling Bag - Regular Size","new_price":31,"old_price":12,"discount":74,"delivery_type":"Free delivery","hidden_stars":4.4,"item_id":29},{"image":"https://i.ibb.co/s9mWhhZ/7c0942598a21.jpg","brand":"ADAMSON","description":"Blue Men Sling Bag - Extra Spacious","new_price":347,"old_price":1199,"discount":71,"delivery_type":"Free delivery","hidden_stars":3.7,"item_id":30},{"image":"https://i.ibb.co/2n9b0T0/01abe9d93ce7.jpg","brand":"Straplt","description":"Black Men & Women Messenger Bag","new_price":296,"old_price":799,"discount":62,"delivery_type":"Free delivery","hidden_stars":3.8,"item_id":31},{"image":"https://i.ibb.co/WfyYMk2/12933590e786.jpg","brand":"Goldstar","description":"Medium 30 L Laptop Backpack Medium 30 L Laptop Backpack...","new_price":499,"old_price":1999,"discount":75,"delivery_type":"Free delivery","hidden_stars":4.2,"item_id":32},{"image":"https://i.ibb.co/L1Vf313/8429020106d8.jpg","brand":"ADAMSON","description":"Multicolor Men Sling Bag - Extra Spacious","new_price":314,"old_price":1199,"discount":73,"delivery_type":"Free delivery","hidden_stars":4.1,"item_id":33},{"image":"https://i.ibb.co/FqHmCv2/140f6d856676.jpg","brand":"Pramadda Pure Luxury","description":"Brown Men Sling Bag - Regular Size","new_price":44,"old_price":1299,"discount":66,"delivery_type":"Free delivery","hidden_stars":3.6,"item_id":34},{"image":"https://i.ibb.co/1T9ymYt/a0a952938d39.jpg","brand":"HAZEL","description":"20 L Gym Duffel Bag - BLACK GYM BAG FOR MEN & WOMEN WIT...","new_price":259,"old_price":999,"discount":74,"delivery_type":"Free delivery","hidden_stars":3.5,"item_id":35},{"image":"https://i.ibb.co/Y07GCsF/632eea3616fe.jpg","brand":"PROVOGUE","description":"Large 40 L Laptop Backpack PR-7801-GREY Multi-Purpose L...","new_price":725,"old_price":49,"discount":85,"delivery_type":"Free delivery","hidden_stars":4.2,"item_id":36},{"image":"https://i.ibb.co/dmfd6y5/ead65bc57478.jpg","brand":"facto","description":"22 L Gym Duffel Bag - boys and girl collage bag school ...","new_price":396,"old_price":1999,"discount":80,"delivery_type":"Free delivery","hidden_stars":4.3,"item_id":37},{"image":"https://i.ibb.co/4jFRqCY/002de79c7627.jpg","brand":"SAMTROH","description":"Men Casual Beige Artificial Leather Wallet - Regular Si...","new_price":219,"old_price":999,"discount":78,"delivery_type":"Free delivery","hidden_stars":3.8,"item_id":38},{"image":"https://i.ibb.co/55hVrQ8/0cc8772dc621.jpg","brand":"AMERICAN TOURISTER","description":"32.5 L Backpack Mist Sch Bag","new_price":829,"old_price":26,"discount":68,"delivery_type":"Free delivery","hidden_stars":4,"item_id":39},{"image":"https://i.ibb.co/Wz1sXgK/ade7a5453f78.jpg","brand":"Goldstar","description":"Medium 28 L Laptop Backpack Medium 28 L Laptop Backpack...","new_price":465,"old_price":1999,"discount":76,"delivery_type":"Free delivery","hidden_stars":3.7,"item_id":40},{"image":"https://i.ibb.co/xmhdgz3/cf5cb6c54633.jpg","brand":"ZIPLINE","description":"Large 36 L Backpack Big Storage bags men :: Casual coll...","new_price":798,"old_price":1899,"discount":57,"delivery_type":"Free delivery","hidden_stars":3.9,"item_id":41},{"image":"https://i.ibb.co/jDqjHjW/9ef830694303.jpg","brand":"Flycraft","description":"Medium 30 L Laptop Backpack simna.1366 navy blue grey c...","new_price":529,"old_price":199,"discount":51,"delivery_type":"Free delivery","hidden_stars":3.7,"item_id":42},{"image":"https://i.ibb.co/JrYhcGs/2e2675273a64.jpg","brand":"Flycraft","description":"Large 35 L Laptop Backpack simna.1378 large 35 L airpor...","new_price":699,"old_price":2999,"discount":76,"delivery_type":"Free delivery","hidden_stars":3.7,"item_id":43},{"image":"https://i.ibb.co/mN0BZkY/c44f676ace50.jpg","brand":"Croma","description":"Small 20 L Laptop Backpack CRXL5206","new_price":229,"old_price":25,"discount":8,"delivery_type":"Free delivery","hidden_stars":3.6,"item_id":44},{"image":"https://i.ibb.co/jHhg0y4/b1a6fe0bb280.jpg","brand":"Flycraft","description":"Medium 30 L Laptop Backpack simna.1366/1 airport blue c...","new_price":529,"old_price":1499,"discount":64,"delivery_type":"Free delivery","hidden_stars":4.4,"item_id":45},{"image":"https://i.ibb.co/qmvYjWV/f349cd9e7f54.jpg","brand":"Gear","description":"Medium 26 L Backpack Jacquard Camo","new_price":719,"old_price":1299,"discount":44,"delivery_type":"Free delivery","hidden_stars":4.2,"item_id":46},{"image":"https://i.ibb.co/WgKb5D1/3a1091430a72.jpg","brand":"ADAMSON","description":"Grey Men Sling Bag - Extra Spacious","new_price":323,"old_price":1199,"discount":73,"delivery_type":"Free delivery","hidden_stars":4.1,"item_id":47},{"image":"https://i.ibb.co/7KGQGtj/2138a518a7d6.jpg","brand":"Lunar","description":"Large 50 L Laptop Backpack High Quality 50L Travel Lapt...","new_price":1156,"old_price":2999,"discount":61,"delivery_type":"Free delivery","hidden_stars":3.9,"item_id":48},{"image":"https://i.ibb.co/CQDWdfY/d6aec1bd3177.jpg","brand":"CRALOFT","description":"Grey Men Sling Bag","new_price":399,"old_price":699,"discount":42,"delivery_type":"Free delivery","hidden_stars":4,"item_id":49},{"image":"https://i.ibb.co/86ZRGVJ/be678d15d075.jpg","brand":"modfrill","description":"Brown Men Sling Bag - Regular Size","new_price":379,"old_price":1999,"discount":81,"delivery_type":"Free delivery","hidden_stars":3.6,"item_id":50},{"image":"https://i.ibb.co/0ZR7x5v/5c4683628024.jpg","brand":"WM WAFA MART","description":"Multicolor Men Sling Bag - Mini","new_price":423,"old_price":1999,"discount":78,"delivery_type":"Free delivery","hidden_stars":4,"item_id":51},{"image":"https://i.ibb.co/LY83QnK/33eb74d29441.jpg","brand":"Isparro","description":"Large 35 L Laptop Backpack Stylish Light Weight Backpac...","new_price":54,"old_price":15,"discount":64,"delivery_type":"Free delivery","hidden_stars":3.8,"item_id":52},{"image":"https://i.ibb.co/4sRfnLF/5854e2cab2e8.jpg","brand":"DEZiRE CRAfTS","description":"Black Men Sling Bag - Extra Spacious","new_price":399,"old_price":1299,"discount":69,"delivery_type":"Free delivery","hidden_stars":4.3,"item_id":53},{"image":"https://i.ibb.co/9tzpnWk/29960153e89a.jpg","brand":"facto","description":"22 L Gym Duffel Bag - men and women college bag travel ...","new_price":399,"old_price":1999,"discount":80,"delivery_type":"Free delivery","hidden_stars":4,"item_id":54},{"image":"https://i.ibb.co/WszFh6z/70b274248347.jpg","brand":"Gear","description":"25 L Gym Duffel Bag - Clubsport - Black","new_price":664,"old_price":2399,"discount":72,"delivery_type":"Free delivery","hidden_stars":4.4,"item_id":55},{"image":"https://i.ibb.co/sQDTjG0/0e87b3982369.jpg","brand":"Lunar","description":"Large 50 L Laptop Backpack High Quality 50L Travel Lapt...","new_price":1156,"old_price":2999,"discount":61,"delivery_type":"Free delivery","hidden_stars":4.2,"item_id":56},{"image":"https://i.ibb.co/NpYQCyt/a68648f7bca2.jpg","brand":"WILD EDGE","description":"Men Green Artificial Leather Wallet - Regular Size","new_price":239,"old_price":999,"discount":76,"delivery_type":"Free delivery","hidden_stars":4.3,"item_id":57},{"image":"https://i.ibb.co/SdL80JD/890af2a3b082.jpg","brand":"AMERICAN TOURISTER","description":"Large 32 L Backpack POPIN CASUAL BACKPACK 02 -MAGNETA","new_price":789,"old_price":259,"discount":69,"delivery_type":"Free delivery","hidden_stars":4.2,"item_id":58},{"image":"https://i.ibb.co/vwJQN4p/66d16bae26a6.jpg","brand":"LOUIS CARON","description":"Medium 30 L Backpack Design Laptop Backpack","new_price":525,"old_price":1699,"discount":69,"delivery_type":"Free delivery","hidden_stars":4.1,"item_id":59},{"image":"https://i.ibb.co/JtQWyZr/41254b06126b.jpg","brand":"Goldstar","description":"Medium 30 L Laptop Backpack Medium 30 L Laptop Backpack...","new_price":474,"old_price":2999,"discount":84,"delivery_type":"Free delivery","hidden_stars":4.2,"item_id":60},{"image":"https://i.ibb.co/q9ZCMrb/977cdfec3fbe.jpg","brand":"Wildcraft","description":"Medium 30 L Backpack Spacy_Mel","new_price":1129,"old_price":2699,"discount":58,"delivery_type":"Free delivery","hidden_stars":4.2,"item_id":61},{"image":"https://i.ibb.co/jWwwYpK/70f4e84beee7.jpg","brand":"Lunar","description":"Large 35 L Backpack Comet","new_price":756,"old_price":1699,"discount":55,"delivery_type":"Free delivery","hidden_stars":3.6,"item_id":62},{"image":"https://i.ibb.co/wMPD0Ch/ff320f994b9b.jpg","brand":"Lunar","description":"Large 35 L Backpack Comet","new_price":756,"old_price":1699,"discount":55,"delivery_type":"Free delivery","hidden_stars":3.6,"item_id":63},{"image":"https://i.ibb.co/WKWbVbY/b2dc3879b2dd.jpg","brand":"PROVOGUE","description":"Large 35 L Laptop Backpack COMET -3 Compartment Premium...","new_price":836,"old_price":1999,"discount":58,"delivery_type":"Free delivery","hidden_stars":3.8,"item_id":64},{"image":"https://i.ibb.co/6WhWKkD/d121283241a3.jpg","brand":"Trillion","description":"Small 20 L Backpack Small backpack perfect for hiking t...","new_price":359,"old_price":999,"discount":64,"delivery_type":"Free delivery","hidden_stars":4.3,"item_id":65},{"image":"https://i.ibb.co/wNmQyr4/9744f515f0e7.jpg","brand":"DEZiRE CRAfTS","description":"Green Men Sling Bag - Extra Spacious","new_price":399,"old_price":1299,"discount":69,"delivery_type":"Free delivery","hidden_stars":3.5,"item_id":66},{"image":"https://i.ibb.co/7XhPtVx/7ac16c496e00.jpg","brand":"ADAMSON","description":"Black Men Messenger Bag - Extra Spacious","new_price":395,"old_price":1299,"discount":69,"delivery_type":"Free delivery","hidden_stars":4.3,"item_id":67},{"image":"https://i.ibb.co/GMDYH5J/ba22c3aa62bb.jpg","brand":"HEROZ","description":"Large 45 L Laptop Backpack Hammer","new_price":121,"old_price":32,"discount":62,"delivery_type":"Free delivery","hidden_stars":4,"item_id":68},{"image":"https://i.ibb.co/qnpbG5b/6c376419859f.jpg","brand":"Swanky","description":"Brown Men & Women Sling Bag","new_price":339,"old_price":999,"discount":66,"delivery_type":"Free delivery","hidden_stars":3.7,"item_id":69},{"image":"https://i.ibb.co/VBLcg44/b7544d268752.jpg","brand":"Pramadda Pure Luxury","description":"Brown Men Sling Bag - Regular Size","new_price":386,"old_price":1499,"discount":74,"delivery_type":"Free delivery","hidden_stars":3.8,"item_id":70},{"image":"https://i.ibb.co/t4LWbQV/051eb4f08aa0.jpg","brand":"Blowzy Bags","description":"Blue Men Sling Bag - Extra Spacious","new_price":426,"old_price":1699,"discount":74,"delivery_type":"Free delivery","hidden_stars":4,"item_id":71},{"image":"https://i.ibb.co/gRB5Pjw/9e6f83dc0d28.jpg","brand":"Lunar","description":"Large 48 L Laptop Backpack Bingo -3 Compartment Premium...","new_price":89,"old_price":1999,"discount":59,"delivery_type":"Free delivery","hidden_stars":3.7,"item_id":72},{"image":"https://i.ibb.co/p0jJf7Q/d6cc2443c4d6.jpg","brand":"TORRENTO","description":"40 L Gym Duffel Bag - STYLISH GYM AND BEST MOVING TRAVE...","new_price":395,"old_price":1299,"discount":69,"delivery_type":"Free delivery","hidden_stars":3.7,"item_id":73},{"image":"https://i.ibb.co/4YYgjVJ/03913e661ab8.jpg","brand":"Javrang","description":"23 L Gym Duffel Bag - Gym Duffel Bag for Fitness| Sport...","new_price":269,"old_price":1499,"discount":82,"delivery_type":"Free delivery","hidden_stars":3.8,"item_id":74},{"image":"https://i.ibb.co/1dHtXPr/564b722575b2.jpg","brand":"SAMTROH","description":"Men Casual Brown Artificial Leather Money Clip - Mini","new_price":219,"old_price":999,"discount":78,"delivery_type":"Free delivery","hidden_stars":4,"item_id":75},{"image":"https://i.ibb.co/qypPyRG/864ccf0f98fa.jpg","brand":"Red Lemon","description":"Large 40 L Laptop Backpack Men and Women RL Enforcer Po...","new_price":2696,"old_price":4999,"discount":46,"delivery_type":"Free delivery","hidden_stars":3.5,"item_id":76},{"image":"https://i.ibb.co/BPHH6rY/cbd27bb7cbcf.jpg","brand":"SAFARI","description":"Medium 26 L Backpack Stroke","new_price":699,"old_price":2599,"discount":73,"delivery_type":"Free delivery","hidden_stars":4.1,"item_id":77},{"image":"https://i.ibb.co/nCKbbqS/232b76424c97.jpg","brand":"Gear","description":"Small 18 L Backpack Eco Backpack 4 Orange Black","new_price":359,"old_price":198,"discount":67,"delivery_type":"Free delivery","hidden_stars":4,"item_id":78},{"image":"https://i.ibb.co/Q6TLfyH/c5a04bb10d2f.jpg","brand":"SAFARI","description":"Medium 26 L Backpack Brute","new_price":699,"old_price":2599,"discount":73,"delivery_type":"Free delivery","hidden_stars":4.5,"item_id":79},{"image":"https://i.ibb.co/SX1025G/03051a84b0f9.jpg","brand":"Lunar","description":"Large 35 L Backpack Comet","new_price":756,"old_price":1699,"discount":55,"delivery_type":"Free delivery","hidden_stars":4.3,"item_id":80}]